{
  "ShowInsuranceResult": {
    "Comments": null,
    "Errors": null,
    "ResultKey": null,
    "Warningss": null,
    "InsurancePlan": {
      "Comments": null,
      "Errors": null,
      "ResultKey": null,
      "Warningss": null,
      "InsurancePlans": [
        {
          "BirthDate": "4/17/1951 12:00:00 AM",
          "Code": 1,
          "CoverInfos": [
            {
              "CoverLimit": "50,000 EUR",
              "TitleEn": "",
              "TitleFa": "پرداخت هزینه بستری شدن در بیمارستان و معالجات پزشکی، به استثناء هزینه های زیبائی، بیماری های مزمن و بیماری هایی که از قبل سابقه داشته باشد. فرانشیز: 25 یورو بجز موارد اورژانسی و ناشی از حادثه و یا بستری شدن در بیمارستان بیش از 24 ساعت "
            },
            {
              "CoverLimit": "Actual expenses",
              "TitleEn": "",
              "TitleFa": "انتقال بیمه شده به نزدیکترین مرکز درمانی در اثر حادثه و یا بیماری، هماهنگی های لازم جهت انتقال به مرکز مجهز تر، استفاده از آمبولانس هوایی و یا بازگشت به ایران در صورت تشخیص پزشک"
            },
            {
              "CoverLimit": "400 EUR",
              "TitleEn": "",
              "TitleFa": "پرداخت هزینه فوریت های دندانپزشکی فقط هزینه هایی که به منظور رفع دندان درد و یا پوسیدگی دندان انجام می­گردد. فرانشیز: 25 یورو"
            },
            {
              "CoverLimit": "Actual expenses",
              "TitleEn": "",
              "TitleFa": "بازگرداندن جسد بیمه شده متوفی به ایران"
            },
            {
              "CoverLimit": "Actual expenses",
              "TitleEn": "",
              "TitleFa": "بازگشت یکی از اعضای بلافصل خانواده به ایران در صورت بستری شدن بیمه شده بیشتر از 10 روز. "
            },
            {
              "CoverLimit": "1500 EUR",
              "TitleEn": "",
              "TitleFa": "مشاوره حقوقی و پرداخت هزینه دعوی بیمه شده در صورتی که بر طبق قانون مدنی کشور مربوطه تحت پیگرد باشد."
            },
            {
              "CoverLimit": "Actual expenses",
              "TitleEn": "",
              "TitleFa": "پرداخت هزینه بازگشت غیر منتظره بیمه شده به دلیل مسائل حاد پزشکی و یا فوت بستگان در صورتیکه نتواند از بلیط اصلی برای بازگشت استفاده نماید. "
            },
            {
              "CoverLimit": "Actual expenses",
              "TitleEn": "",
              "TitleFa": "ارسال داروهای ضروری با تائید پزشک به کشوری که بیمه شده به آن سفر کرده است."
            },
            {
              "CoverLimit": "250 EUR",
              "TitleEn": "",
              "TitleFa": "پرداخت هزینه خرید های اضطراری ( البسه و لوازم بهداشت شخصی) ناشی از تأخیر در تحویل بار که بیش از 12 ساعت باشد. هزینه مربوطه فقط در صورتی پرداخت می شود که بیمه شده به مقصدی به جز کشور ایران سفر کند. ارائه اصل فاکتورهای خرید الزامی می باشد."
            },
            {
              "CoverLimit": "800 EUR",
              "TitleEn": "",
              "TitleFa": "پرداخت هزینه خرید های اضطراری ناشی از گم شدن چمدان ها . در صورت استفاده از بند تأخیر در تحویل چمدان ها، قابل ارائه نخواهد بود."
            },
            {
              "CoverLimit": "200 EUR",
              "TitleEn": "",
              "TitleFa": "راهنمائی و کمک رسانی در خصوص مفقود شدن گذرنامه، گواهینامه بین المللی و مدارک شناسائی در خارج از کشور و پرداخت هزینه های تهیه مجدد آنها."
            },
            {
              "CoverLimit": "Actual expenses",
              "TitleEn": "",
              "TitleFa": "امداد رسانی در یافتن و ارسال بار و ملزومات شخصی."
            },
            {
              "CoverLimit": "Actual expenses",
              "TitleEn": "",
              "TitleFa": "انتقال پیام های فوری و همچنین ارائه نشانی مراکز درمانی، داروخانه ها، پزشکان به بیمه شده در خارج از کشور"
            },
            {
              "CoverLimit": "180 EUR",
              "TitleEn": "",
              "TitleFa": "پرداخت هزینه هایی که در صورت تأخیر هواپیما ( بیش از 6 ساعت ) متوجه بیمه گذار خواهد بود ( اقامت در هتل و صرف غذا ) با ارائه اصل صورتحساب و تائیدیه شرکت هواپیمایی "
            },
            {
              "CoverLimit": "850 EUR",
              "TitleEn": "",
              "TitleFa": "ارسال وجه الضمان"
            },
            {
              "CoverLimit": "850 EUR",
              "TitleEn": "",
              "TitleFa": "ارسال پول نقد"
            }
          ],
          "CoverLimit": "50,000 EUR",
          "Discount": 0,
          "DiscountPercentage": 0,
          "PassengerKey": "1",
          "Price": 723760,
          "Title": "طرح پایه 50,000 یورو",
          "TitleEnglish": "50,000 EUR Plan"
        }
      ],
      "SearchKey": "042bf5a3-4b4e-485f-851b-e0cf25b433a3"
    },
    "TravelInsurance": {
      "Comments": null,
      "Errors": null,
      "ResultKey": null,
      "Warningss": null,
      "TravelInsurances": [
        {
          "InsID": "3",
          "TravelInsuranceCoverages": [
            {
              "TravelInsuranceCoverageCategory": {
                "TravelInsuranceCoverageCatID": "1",
                "TravelInsuranceCoverageCatTile": null
              },
              "TravelInsuranceCoverageID": "1000",
              "TravelInsuranceCoverageTile": "جبران هزینه‎‌های ناشی از کنسلی بلیط هواپیما یا کنسلی هتل محل اقامت به دلیل شرایط حاد اورژانسی بیمه شده که باعث بستری ایشان یا همراه وی شود.*همراه بیمه شده ( همراه سفر)یکی از بستگان درجه اول یا بلافصل بیمه شده شامل پدر، مادر، خواهر، همسر، فرزندیا فرزند خوانده قانونی است که با بیمه شده در یک پرواز و  به یک مقصد عازم مسافرت است",
              "TravelInsuranceCoverageVal": "250 یورو"
            },
            {
              "TravelInsuranceCoverageCategory": {
                "TravelInsuranceCoverageCatID": "1",
                "TravelInsuranceCoverageCatTile": null
              },
              "TravelInsuranceCoverageID": "1001",
              "TravelInsuranceCoverageTile": "جبران هزینه‌های ناشی از کنسلی بلیط هواپیما یا کنسلی هتل محل اقامت به دلیل بستری شدن یکی از اعضای بلافصل یا درجه اول بیمه شده دربیمارستان به دلیل شرایط اورژانسی (به جز بستگانی که در مقصد سفر بیمه شده مقیم هستند) - حداکثر 15 روز قبل از عزیمت به سفر.*همراه بیمه شده ( همراه سفر)یکی از بستگان درجه اول یا بلافصل بیمه شده شامل پدر، مادر، خواهر، همسر، فرزند یا فرزندخوانده قانونی است که با بیمه شده در یک پرواز و  به یک مقصد عازم مسافرت است.",
              "TravelInsuranceCoverageVal": "250 یورو"
            },
            {
              "TravelInsuranceCoverageCategory": {
                "TravelInsuranceCoverageCatID": "1",
                "TravelInsuranceCoverageCatTile": null
              },
              "TravelInsuranceCoverageID": "1003",
              "TravelInsuranceCoverageTile": "فوت بیمه شده",
              "TravelInsuranceCoverageVal": "250 یورو"
            },
            {
              "TravelInsuranceCoverageCategory": {
                "TravelInsuranceCoverageCatID": "1",
                "TravelInsuranceCoverageCatTile": null
              },
              "TravelInsuranceCoverageID": "1004",
              "TravelInsuranceCoverageTile": "جبران هزینه‌های ناشی از کنسلی بلیط هواپیما یا هتل محل اقامت به دلیل فوت یکی از بستگان بلافصل بیمه شده ( به جز بستگانی که در مقصد سفربیمه شده مقیم هستند)- حداکثر یک ماه قبل سفر به شرط این که متوفی بعد از خرید بیمه نامه فوت شده باشد.",
              "TravelInsuranceCoverageVal": "250 یورو"
            },
            {
              "TravelInsuranceCoverageCategory": {
                "TravelInsuranceCoverageCatID": "1",
                "TravelInsuranceCoverageCatTile": null
              },
              "TravelInsuranceCoverageID": "1005",
              "TravelInsuranceCoverageTile": "جبران هزینه‌های ناشی از کنسلی بلیط هواپیما یا کنسلی هتل محل اقامت به دلیل بستری شدن یکی از اعضای بلافصل یا درجه اول بیمه شده دربیمارستان به دلیل شرایط اورژانسی (به جز بستگانی که در مقصد سفر بیمه شده مقیم هستند) - حداکثر 30 روز قبل از عزیمت به سفر.همراه بیمه شده ( همراه سفر)",
              "TravelInsuranceCoverageVal": "250 یورو"
            },
            {
              "TravelInsuranceCoverageCategory": {
                "TravelInsuranceCoverageCatID": "2",
                "TravelInsuranceCoverageCatTile": null
              },
              "TravelInsuranceCoverageID": "1008",
              "TravelInsuranceCoverageTile": "انتقال بیمه شده به نزدیکترین مرکز درمانی در اثر حادثه و یا بیماری هماهنگی های لازم جهت انتقال بیمه شده به مرکز درمانی مجهزتر، استفاده ازآمبولانس هوایی و یا بازگرداندن بیمه شده به ایران در صورت نیاز.",
              "TravelInsuranceCoverageVal": "بدون سقف"
            },
            {
              "TravelInsuranceCoverageCategory": {
                "TravelInsuranceCoverageCatID": "2",
                "TravelInsuranceCoverageCatTile": null
              },
              "TravelInsuranceCoverageID": "1009",
              "TravelInsuranceCoverageTile": "جبران هزینه‌های برگشت زود هنگام مسافر به دلیل شرایط حاد اورژانسی بیمه شده یا همراه وی در سفر.*همراه بیمه شده ( همراه سفر)یکی از بستگان درجه اول یا بلافصل بیمه شده شامل پدر، مادر، خواهر، همسر، فرزند یا فرزند خوانده قانونی است که با بیمه شده در یک پرواز و  به یک مقصد عازم مسافرت است.",
              "TravelInsuranceCoverageVal": "250 یورو"
            },
            {
              "TravelInsuranceCoverageCategory": {
                "TravelInsuranceCoverageCatID": "2",
                "TravelInsuranceCoverageCatTile": null
              },
              "TravelInsuranceCoverageID": "1011",
              "TravelInsuranceCoverageTile": "پرداخت هزینه بستری شدن در بیمارستان و معالجات پزشکی (با استثناء هزینه های زیبایی ، بیماری های که از قبل سابقه داشته باشد ) فرانشیز 25 یورو",
              "TravelInsuranceCoverageVal": "20,000 یورو"
            },
            {
              "TravelInsuranceCoverageCategory": {
                "TravelInsuranceCoverageCatID": "2",
                "TravelInsuranceCoverageCatTile": null
              },
              "TravelInsuranceCoverageID": "1012",
              "TravelInsuranceCoverageTile": "پرداخت هزینه فوریت های دندانپزشکی ، فرانشیز 25 یورو",
              "TravelInsuranceCoverageVal": "150 یورو"
            },
            {
              "TravelInsuranceCoverageCategory": {
                "TravelInsuranceCoverageCatID": "2",
                "TravelInsuranceCoverageCatTile": null
              },
              "TravelInsuranceCoverageID": "1013",
              "TravelInsuranceCoverageTile": "تجویز دارو",
              "TravelInsuranceCoverageVal": "200 یورو"
            },
            {
              "TravelInsuranceCoverageCategory": {
                "TravelInsuranceCoverageCatID": "2",
                "TravelInsuranceCoverageCatTile": null
              },
              "TravelInsuranceCoverageID": "1016",
              "TravelInsuranceCoverageTile": "پرداخت هزینه های بازگشت کودکان زیر 15 سال بیمه شده به همراه یک سرپرست به ایران در صورت فوت یا بستری شدن بیمه شده",
              "TravelInsuranceCoverageVal": "بدون سقف"
            },
            {
              "TravelInsuranceCoverageCategory": {
                "TravelInsuranceCoverageCatID": "2",
                "TravelInsuranceCoverageCatTile": null
              },
              "TravelInsuranceCoverageID": "1017",
              "TravelInsuranceCoverageTile": "پرداخت هزینه های جابه جایی اورژانسی به دلیل مشکلات پزشکی تا اولین مرکز درمانی",
              "TravelInsuranceCoverageVal": "10,000 یورو"
            },
            {
              "TravelInsuranceCoverageCategory": {
                "TravelInsuranceCoverageCatID": "2",
                "TravelInsuranceCoverageCatTile": null
              },
              "TravelInsuranceCoverageID": "1018",
              "TravelInsuranceCoverageTile": "ارسال دارو های ضروری با تائید پرشکی به کشوری که بیمه شده درآن بستری می باشد.",
              "TravelInsuranceCoverageVal": "بدون سقف"
            },
            {
              "TravelInsuranceCoverageCategory": {
                "TravelInsuranceCoverageCatID": "2",
                "TravelInsuranceCoverageCatTile": null
              },
              "TravelInsuranceCoverageID": "1019",
              "TravelInsuranceCoverageTile": "ارسال پیام های فوری بیمه شده به فردی که توسط وی معرفی شده و همچنین ارائه نشانی مراکز درمانی، داروخانه ها، پزشکان به بیمه شده در خارج از کشور",
              "TravelInsuranceCoverageVal": "بدون سقف"
            },
            {
              "TravelInsuranceCoverageCategory": {
                "TravelInsuranceCoverageCatID": "2",
                "TravelInsuranceCoverageCatTile": null
              },
              "TravelInsuranceCoverageID": "1020",
              "TravelInsuranceCoverageTile": "کمک رسان در دسترس 24 ساعته،7 روز هفته به زبان فارسی",
              "TravelInsuranceCoverageVal": "تحت پوشش"
            },
            {
              "TravelInsuranceCoverageCategory": {
                "TravelInsuranceCoverageCatID": "2",
                "TravelInsuranceCoverageCatTile": null
              },
              "TravelInsuranceCoverageID": "1022",
              "TravelInsuranceCoverageTile": "پرداخت هزینه بازگشت غیر منتظره بیمه شده به دلیل مسائل حاد پزشکی ",
              "TravelInsuranceCoverageVal": "10,000 یورو"
            },
            {
              "TravelInsuranceCoverageCategory": {
                "TravelInsuranceCoverageCatID": "2",
                "TravelInsuranceCoverageCatTile": null
              },
              "TravelInsuranceCoverageID": "1023",
              "TravelInsuranceCoverageTile": "بازگرداندن جسد بیمه شده متوفی به ایران در صورت فوت وی درخارج از کشور",
              "TravelInsuranceCoverageVal": "10,000 یورو"
            },
            {
              "TravelInsuranceCoverageCategory": {
                "TravelInsuranceCoverageCatID": "2",
                "TravelInsuranceCoverageCatTile": null
              },
              "TravelInsuranceCoverageID": "1024",
              "TravelInsuranceCoverageTile": "پرداخت هزینه بازگشت غیر منتظره بیمه شده به دلیل مسائل حاد پزشکی و یا فوت بستگان در صورتیکه نتواند از بلیط اصلی برای بازگشت استفاده نماید.",
              "TravelInsuranceCoverageVal": "بدون سقف"
            },
            {
              "TravelInsuranceCoverageCategory": {
                "TravelInsuranceCoverageCatID": "2",
                "TravelInsuranceCoverageCatTile": null
              },
              "TravelInsuranceCoverageID": "1028",
              "TravelInsuranceCoverageTile": "یافتن بار و ارسال بار و ملزومات شخصی ( طبق شرایط عمومی بیمه نامه مسافرتی شرکت کمک رسان ایران )",
              "TravelInsuranceCoverageVal": "بدون سقف"
            },
            {
              "TravelInsuranceCoverageCategory": {
                "TravelInsuranceCoverageCatID": "2",
                "TravelInsuranceCoverageCatTile": null
              },
              "TravelInsuranceCoverageID": "1029",
              "TravelInsuranceCoverageTile": "هزینه جبران مفقود شدن یا گم شدن جامه دان و اسباب همراه ( به استثنا دزدی و سرقت )",
              "TravelInsuranceCoverageVal": "200 یورو"
            },
            {
              "TravelInsuranceCoverageCategory": {
                "TravelInsuranceCoverageCatID": "2",
                "TravelInsuranceCoverageCatTile": null
              },
              "TravelInsuranceCoverageID": "1030",
              "TravelInsuranceCoverageTile": "راهنمایی و کمک رسانی به بیمه شده در صورت سرقت و یا مفقود شدن مدارک مسافرتی وی.",
              "TravelInsuranceCoverageVal": "400 یورو"
            },
            {
              "TravelInsuranceCoverageCategory": {
                "TravelInsuranceCoverageCatID": "2",
                "TravelInsuranceCoverageCatTile": null
              },
              "TravelInsuranceCoverageID": "1031",
              "TravelInsuranceCoverageTile": "پرداخت هزینه خریدهای اضطراری، در صورتیکه تأخیر در تحویل بار کنترل شده وی بیش از 48 ساعت به طول بیانجامد.",
              "TravelInsuranceCoverageVal": "400 یورو"
            },
            {
              "TravelInsuranceCoverageCategory": {
                "TravelInsuranceCoverageCatID": "2",
                "TravelInsuranceCoverageCatTile": null
              },
              "TravelInsuranceCoverageID": "1032",
              "TravelInsuranceCoverageTile": "پرداخت هزینه خریدهای اضطراری، در صورتیکه تأخیر در تحویل بار کنترل شده وی بیش از 12 ساعت به طول بیانجامد.",
              "TravelInsuranceCoverageVal": "100 یورو"
            },
            {
              "TravelInsuranceCoverageCategory": {
                "TravelInsuranceCoverageCatID": "2",
                "TravelInsuranceCoverageCatTile": null
              },
              "TravelInsuranceCoverageID": "1033",
              "TravelInsuranceCoverageTile": "مشاوره حقوقی و پرداخت هزینه های دعاوی  بیمه شده در صورتی که طبق قانون مدنی کشور مربوطه تحت پیگرد باشد.",
              "TravelInsuranceCoverageVal": "1,500 یورو"
            },
            {
              "TravelInsuranceCoverageCategory": {
                "TravelInsuranceCoverageCatID": "2",
                "TravelInsuranceCoverageCatTile": null
              },
              "TravelInsuranceCoverageID": "1034",
              "TravelInsuranceCoverageTile": "ارسال وجه الضمان",
              "TravelInsuranceCoverageVal": "850 یورو"
            },
            {
              "TravelInsuranceCoverageCategory": {
                "TravelInsuranceCoverageCatID": "2",
                "TravelInsuranceCoverageCatTile": null
              },
              "TravelInsuranceCoverageID": "1035",
              "TravelInsuranceCoverageTile": "حواله وجه نقد",
              "TravelInsuranceCoverageVal": "850 یورو"
            },
            {
              "TravelInsuranceCoverageCategory": {
                "TravelInsuranceCoverageCatID": "2",
                "TravelInsuranceCoverageCatTile": null
              },
              "TravelInsuranceCoverageID": "1036",
              "TravelInsuranceCoverageTile": "پرداخت هزینه رفت و برگشت یک نفر به درخواست بیمه شده از ایران به محل بستری در صورتیکه که بیمه شده بیش از 10 روز متوالی در بیمارستان بستری باشد.(شامل بلیط رفت و برگشت و مخارج اقامت)",
              "TravelInsuranceCoverageVal": "60یورو برای هر روز(15 روز متوالی)"
            },
            {
              "TravelInsuranceCoverageCategory": {
                "TravelInsuranceCoverageCatID": "2",
                "TravelInsuranceCoverageCatTile": null
              },
              "TravelInsuranceCoverageID": "1037",
              "TravelInsuranceCoverageTile": "بازگشت یکی از اعضای بلافصل خانواده به کشور محل اقامت در صورت بستری شدن بیمه شده بیش از 10 روز",
              "TravelInsuranceCoverageVal": "بدون سقف"
            },
            {
              "TravelInsuranceCoverageCategory": {
                "TravelInsuranceCoverageCatID": "2",
                "TravelInsuranceCoverageCatTile": null
              },
              "TravelInsuranceCoverageID": "1039",
              "TravelInsuranceCoverageTile": "پرداخت هزینه هایی که در صورت تاخیر هواپیما متوجه بیمه گذار خواهد بود ( اقامت در هتل صرف غذا ) با ارائه اصل صورتحساب و با تاییدیه شرکت هواپیمایی",
              "TravelInsuranceCoverageVal": "180 یورو"
            },
            {
              "TravelInsuranceCoverageCategory": {
                "TravelInsuranceCoverageCatID": "2",
                "TravelInsuranceCoverageCatTile": null
              },
              "TravelInsuranceCoverageID": "1040",
              "TravelInsuranceCoverageTile": "جبران هزینه‌های بازگشت زودهنگام بیمه شده به دلیل فوت یکی از بستگان بلافصل بیمه شده (به جز بستگانی که در مقصد سفر بیمه شده مقیم هستند)",
              "TravelInsuranceCoverageVal": "250 یورو"
            }
          ],
          "TravelInsuranceID": "-1",
          "TravelInsurancePricePP": {
            "Amount": 150000,
            "CurrencyCode": "IRR"
          },
          "TravelInsuranceTile": "بیمه مسافرتی سامان  - طرح پایه"
        },
        {
          "InsID": "4",
          "TravelInsuranceCoverages": [
            {
              "TravelInsuranceCoverageCategory": {
                "TravelInsuranceCoverageCatID": "1",
                "TravelInsuranceCoverageCatTile": null
              },
              "TravelInsuranceCoverageID": "1000",
              "TravelInsuranceCoverageTile": "جبران هزینه‎‌های ناشی از کنسلی بلیط هواپیما یا کنسلی هتل محل اقامت به دلیل شرایط حاد اورژانسی بیمه شده که باعث بستری ایشان یا همراه وی شود.*همراه بیمه شده ( همراه سفر)یکی از بستگان درجه اول یا بلافصل بیمه شده شامل پدر، مادر، خواهر، همسر، فرزندیا فرزند خوانده قانونی است که با بیمه شده در یک پرواز و  به یک مقصد عازم مسافرت است",
              "TravelInsuranceCoverageVal": "500 یورو"
            },
            {
              "TravelInsuranceCoverageCategory": {
                "TravelInsuranceCoverageCatID": "1",
                "TravelInsuranceCoverageCatTile": null
              },
              "TravelInsuranceCoverageID": "1001",
              "TravelInsuranceCoverageTile": "جبران هزینه‌های ناشی از کنسلی بلیط هواپیما یا کنسلی هتل محل اقامت به دلیل بستری شدن یکی از اعضای بلافصل یا درجه اول بیمه شده دربیمارستان به دلیل شرایط اورژانسی (به جز بستگانی که در مقصد سفر بیمه شده مقیم هستند) - حداکثر 15 روز قبل از عزیمت به سفر.*همراه بیمه شده ( همراه سفر)یکی از بستگان درجه اول یا بلافصل بیمه شده شامل پدر، مادر، خواهر، همسر، فرزند یا فرزندخوانده قانونی است که با بیمه شده در یک پرواز و  به یک مقصد عازم مسافرت است.",
              "TravelInsuranceCoverageVal": "500 یورو"
            },
            {
              "TravelInsuranceCoverageCategory": {
                "TravelInsuranceCoverageCatID": "1",
                "TravelInsuranceCoverageCatTile": null
              },
              "TravelInsuranceCoverageID": "1002",
              "TravelInsuranceCoverageTile": "جبران هزینه‌های ناشی از کنسلی بلیط هواپیما یا هتل محل اقامت به دلیل عوارض ناشی از بارداری در 31 هفته اول بارداری بیمه شده یا یکی از اعضای بلافصل بیمه شده ( عوارض بارداری جندمین بارداری یا درمان عدم بارداری شامل این پوشش نیست).",
              "TravelInsuranceCoverageVal": "500 یورو"
            },
            {
              "TravelInsuranceCoverageCategory": {
                "TravelInsuranceCoverageCatID": "1",
                "TravelInsuranceCoverageCatTile": null
              },
              "TravelInsuranceCoverageID": "1003",
              "TravelInsuranceCoverageTile": "فوت بیمه شده",
              "TravelInsuranceCoverageVal": "500 یورو"
            },
            {
              "TravelInsuranceCoverageCategory": {
                "TravelInsuranceCoverageCatID": "1",
                "TravelInsuranceCoverageCatTile": null
              },
              "TravelInsuranceCoverageID": "1004",
              "TravelInsuranceCoverageTile": "جبران هزینه‌های ناشی از کنسلی بلیط هواپیما یا هتل محل اقامت به دلیل فوت یکی از بستگان بلافصل بیمه شده ( به جز بستگانی که در مقصد سفربیمه شده مقیم هستند)- حداکثر یک ماه قبل سفر به شرط این که متوفی بعد از خرید بیمه نامه فوت شده باشد.",
              "TravelInsuranceCoverageVal": "500 یورو"
            },
            {
              "TravelInsuranceCoverageCategory": {
                "TravelInsuranceCoverageCatID": "1",
                "TravelInsuranceCoverageCatTile": null
              },
              "TravelInsuranceCoverageID": "1005",
              "TravelInsuranceCoverageTile": "جبران هزینه‌های ناشی از کنسلی بلیط هواپیما یا کنسلی هتل محل اقامت به دلیل بستری شدن یکی از اعضای بلافصل یا درجه اول بیمه شده دربیمارستان به دلیل شرایط اورژانسی (به جز بستگانی که در مقصد سفر بیمه شده مقیم هستند) - حداکثر 30 روز قبل از عزیمت به سفر.همراه بیمه شده ( همراه سفر)",
              "TravelInsuranceCoverageVal": "500 یورو"
            },
            {
              "TravelInsuranceCoverageCategory": {
                "TravelInsuranceCoverageCatID": "1",
                "TravelInsuranceCoverageCatTile": null
              },
              "TravelInsuranceCoverageID": "1006",
              "TravelInsuranceCoverageTile": "جبران هزینه‌های ناشی از کنسلی بلیط هواپیما و یا هتل محل اقامت به دلیل اعلام رسمی وزرات امور خارجه جمهوری اسلامی ایران که در آن سفر افرادایرانی (مقیم ایران) به نقطه عزیمت  منع شده باشد، به شرط این که اعلامیه یاد شده پس از خرید بیمه نامه صورت پذیرفته باشد.",
              "TravelInsuranceCoverageVal": "500 یورو"
            },
            {
              "TravelInsuranceCoverageCategory": {
                "TravelInsuranceCoverageCatID": "1",
                "TravelInsuranceCoverageCatTile": null
              },
              "TravelInsuranceCoverageID": "1007",
              "TravelInsuranceCoverageTile": "جبران هزینه‌های ناشی از کنسلی بلیط هواپیما یا هتل محل اقامت به دلیل ازدست دادن پرواز به دلیل تصادف یا تاخیر وسیله حمل و نقل به فرودگاه محل عزیمت (این پوشش صرفا به شرکت تاکسی طرف قرارداد با شرکت بیمه سامان اعطا می شود).",
              "TravelInsuranceCoverageVal": "500 یورو"
            },
            {
              "TravelInsuranceCoverageCategory": {
                "TravelInsuranceCoverageCatID": "2",
                "TravelInsuranceCoverageCatTile": null
              },
              "TravelInsuranceCoverageID": "1008",
              "TravelInsuranceCoverageTile": "انتقال بیمه شده به نزدیکترین مرکز درمانی در اثر حادثه و یا بیماری هماهنگی های لازم جهت انتقال بیمه شده به مرکز درمانی مجهزتر، استفاده ازآمبولانس هوایی و یا بازگرداندن بیمه شده به ایران در صورت نیاز.",
              "TravelInsuranceCoverageVal": "بدون سقف"
            },
            {
              "TravelInsuranceCoverageCategory": {
                "TravelInsuranceCoverageCatID": "2",
                "TravelInsuranceCoverageCatTile": null
              },
              "TravelInsuranceCoverageID": "1009",
              "TravelInsuranceCoverageTile": "جبران هزینه‌های برگشت زود هنگام مسافر به دلیل شرایط حاد اورژانسی بیمه شده یا همراه وی در سفر.*همراه بیمه شده ( همراه سفر)یکی از بستگان درجه اول یا بلافصل بیمه شده شامل پدر، مادر، خواهر، همسر، فرزند یا فرزند خوانده قانونی است که با بیمه شده در یک پرواز و  به یک مقصد عازم مسافرت است.",
              "TravelInsuranceCoverageVal": "500 یورو"
            },
            {
              "TravelInsuranceCoverageCategory": {
                "TravelInsuranceCoverageCatID": "2",
                "TravelInsuranceCoverageCatTile": null
              },
              "TravelInsuranceCoverageID": "1010",
              "TravelInsuranceCoverageTile": "مسئولیت شخصی",
              "TravelInsuranceCoverageVal": "2,000 یورو"
            },
            {
              "TravelInsuranceCoverageCategory": {
                "TravelInsuranceCoverageCatID": "2",
                "TravelInsuranceCoverageCatTile": null
              },
              "TravelInsuranceCoverageID": "1011",
              "TravelInsuranceCoverageTile": "پرداخت هزینه بستری شدن در بیمارستان و معالجات پزشکی (با استثناء هزینه های زیبایی ، بیماری های که از قبل سابقه داشته باشد ) فرانشیز 25 یورو",
              "TravelInsuranceCoverageVal": "20,000 یورو"
            },
            {
              "TravelInsuranceCoverageCategory": {
                "TravelInsuranceCoverageCatID": "2",
                "TravelInsuranceCoverageCatTile": null
              },
              "TravelInsuranceCoverageID": "1012",
              "TravelInsuranceCoverageTile": "پرداخت هزینه فوریت های دندانپزشکی ، فرانشیز 25 یورو",
              "TravelInsuranceCoverageVal": "250 یورو"
            },
            {
              "TravelInsuranceCoverageCategory": {
                "TravelInsuranceCoverageCatID": "2",
                "TravelInsuranceCoverageCatTile": null
              },
              "TravelInsuranceCoverageID": "1013",
              "TravelInsuranceCoverageTile": "تجویز دارو",
              "TravelInsuranceCoverageVal": "400 یورو"
            },
            {
              "TravelInsuranceCoverageCategory": {
                "TravelInsuranceCoverageCatID": "2",
                "TravelInsuranceCoverageCatTile": null
              },
              "TravelInsuranceCoverageID": "1014",
              "TravelInsuranceCoverageTile": "هزینه های هتل (مربوط به دوران نقاهت و بستری)",
              "TravelInsuranceCoverageVal": "400 یورو"
            },
            {
              "TravelInsuranceCoverageCategory": {
                "TravelInsuranceCoverageCatID": "2",
                "TravelInsuranceCoverageCatTile": null
              },
              "TravelInsuranceCoverageID": "1015",
              "TravelInsuranceCoverageTile": "هزینه های هتل همراهان وبستگان (در زمان بستری بیمه شده)",
              "TravelInsuranceCoverageVal": "300 یورو"
            },
            {
              "TravelInsuranceCoverageCategory": {
                "TravelInsuranceCoverageCatID": "2",
                "TravelInsuranceCoverageCatTile": null
              },
              "TravelInsuranceCoverageID": "1016",
              "TravelInsuranceCoverageTile": "پرداخت هزینه های بازگشت کودکان زیر 15 سال بیمه شده به همراه یک سرپرست به ایران در صورت فوت یا بستری شدن بیمه شده",
              "TravelInsuranceCoverageVal": "بدون سقف"
            },
            {
              "TravelInsuranceCoverageCategory": {
                "TravelInsuranceCoverageCatID": "2",
                "TravelInsuranceCoverageCatTile": null
              },
              "TravelInsuranceCoverageID": "1017",
              "TravelInsuranceCoverageTile": "پرداخت هزینه های جابه جایی اورژانسی به دلیل مشکلات پزشکی تا اولین مرکز درمانی",
              "TravelInsuranceCoverageVal": "بدون سقف"
            },
            {
              "TravelInsuranceCoverageCategory": {
                "TravelInsuranceCoverageCatID": "2",
                "TravelInsuranceCoverageCatTile": null
              },
              "TravelInsuranceCoverageID": "1018",
              "TravelInsuranceCoverageTile": "ارسال دارو های ضروری با تائید پرشکی به کشوری که بیمه شده درآن بستری می باشد.",
              "TravelInsuranceCoverageVal": "بدون سقف"
            },
            {
              "TravelInsuranceCoverageCategory": {
                "TravelInsuranceCoverageCatID": "2",
                "TravelInsuranceCoverageCatTile": null
              },
              "TravelInsuranceCoverageID": "1019",
              "TravelInsuranceCoverageTile": "ارسال پیام های فوری بیمه شده به فردی که توسط وی معرفی شده و همچنین ارائه نشانی مراکز درمانی، داروخانه ها، پزشکان به بیمه شده در خارج از کشور",
              "TravelInsuranceCoverageVal": "بدون سقف"
            },
            {
              "TravelInsuranceCoverageCategory": {
                "TravelInsuranceCoverageCatID": "2",
                "TravelInsuranceCoverageCatTile": null
              },
              "TravelInsuranceCoverageID": "1020",
              "TravelInsuranceCoverageTile": "کمک رسان در دسترس 24 ساعته،7 روز هفته به زبان فارسی",
              "TravelInsuranceCoverageVal": "تحت پوشش"
            },
            {
              "TravelInsuranceCoverageCategory": {
                "TravelInsuranceCoverageCatID": "2",
                "TravelInsuranceCoverageCatTile": null
              },
              "TravelInsuranceCoverageID": "1021",
              "TravelInsuranceCoverageTile": "هزینه جستجو ونجات بیمه شده",
              "TravelInsuranceCoverageVal": "3,000 یورو"
            },
            {
              "TravelInsuranceCoverageCategory": {
                "TravelInsuranceCoverageCatID": "2",
                "TravelInsuranceCoverageCatTile": null
              },
              "TravelInsuranceCoverageID": "1022",
              "TravelInsuranceCoverageTile": "پرداخت هزینه بازگشت غیر منتظره بیمه شده به دلیل مسائل حاد پزشکی ",
              "TravelInsuranceCoverageVal": "10,000 یورو"
            },
            {
              "TravelInsuranceCoverageCategory": {
                "TravelInsuranceCoverageCatID": "2",
                "TravelInsuranceCoverageCatTile": null
              },
              "TravelInsuranceCoverageID": "1023",
              "TravelInsuranceCoverageTile": "بازگرداندن جسد بیمه شده متوفی به ایران در صورت فوت وی درخارج از کشور",
              "TravelInsuranceCoverageVal": "10,000 یورو"
            },
            {
              "TravelInsuranceCoverageCategory": {
                "TravelInsuranceCoverageCatID": "2",
                "TravelInsuranceCoverageCatTile": null
              },
              "TravelInsuranceCoverageID": "1024",
              "TravelInsuranceCoverageTile": "پرداخت هزینه بازگشت غیر منتظره بیمه شده به دلیل مسائل حاد پزشکی و یا فوت بستگان در صورتیکه نتواند از بلیط اصلی برای بازگشت استفاده نماید.",
              "TravelInsuranceCoverageVal": "بدون سقف"
            },
            {
              "TravelInsuranceCoverageCategory": {
                "TravelInsuranceCoverageCatID": "2",
                "TravelInsuranceCoverageCatTile": null
              },
              "TravelInsuranceCoverageID": "1025",
              "TravelInsuranceCoverageTile": "کنسل شدن سفر به دلیل فوت بیمه شده (هزینه های تور بلیط هواپیما)",
              "TravelInsuranceCoverageVal": "500 یورو"
            },
            {
              "TravelInsuranceCoverageCategory": {
                "TravelInsuranceCoverageCatID": "2",
                "TravelInsuranceCoverageCatTile": null
              },
              "TravelInsuranceCoverageID": "1026",
              "TravelInsuranceCoverageTile": "هزینه های کنسل شدن سفر (شامل تور وبلیط)به دلیل فوت بستگان بلا فصل حد اکثر 14 روز قبل سفر",
              "TravelInsuranceCoverageVal": "300 یورو"
            },
            {
              "TravelInsuranceCoverageCategory": {
                "TravelInsuranceCoverageCatID": "2",
                "TravelInsuranceCoverageCatTile": null
              },
              "TravelInsuranceCoverageID": "1027",
              "TravelInsuranceCoverageTile": "هزینه های کنسل شدن سفر (شامل تور وبلیط)به دلیل بستری شدن بیمه شده به صورتی که بیمه شده تا زمان سفر بستری باشد",
              "TravelInsuranceCoverageVal": "400 یورو"
            },
            {
              "TravelInsuranceCoverageCategory": {
                "TravelInsuranceCoverageCatID": "2",
                "TravelInsuranceCoverageCatTile": null
              },
              "TravelInsuranceCoverageID": "1028",
              "TravelInsuranceCoverageTile": "یافتن بار و ارسال بار و ملزومات شخصی ( طبق شرایط عمومی بیمه نامه مسافرتی شرکت کمک رسان ایران )",
              "TravelInsuranceCoverageVal": "بدون سقف"
            },
            {
              "TravelInsuranceCoverageCategory": {
                "TravelInsuranceCoverageCatID": "2",
                "TravelInsuranceCoverageCatTile": null
              },
              "TravelInsuranceCoverageID": "1029",
              "TravelInsuranceCoverageTile": "هزینه جبران مفقود شدن یا گم شدن جامه دان و اسباب همراه ( به استثنا دزدی و سرقت )",
              "TravelInsuranceCoverageVal": "400 یورو"
            },
            {
              "TravelInsuranceCoverageCategory": {
                "TravelInsuranceCoverageCatID": "2",
                "TravelInsuranceCoverageCatTile": null
              },
              "TravelInsuranceCoverageID": "1030",
              "TravelInsuranceCoverageTile": "راهنمایی و کمک رسانی به بیمه شده در صورت سرقت و یا مفقود شدن مدارک مسافرتی وی.",
              "TravelInsuranceCoverageVal": "800 یورو"
            },
            {
              "TravelInsuranceCoverageCategory": {
                "TravelInsuranceCoverageCatID": "2",
                "TravelInsuranceCoverageCatTile": null
              },
              "TravelInsuranceCoverageID": "1031",
              "TravelInsuranceCoverageTile": "پرداخت هزینه خریدهای اضطراری، در صورتیکه تأخیر در تحویل بار کنترل شده وی بیش از 48 ساعت به طول بیانجامد.",
              "TravelInsuranceCoverageVal": "800 یورو"
            },
            {
              "TravelInsuranceCoverageCategory": {
                "TravelInsuranceCoverageCatID": "2",
                "TravelInsuranceCoverageCatTile": null
              },
              "TravelInsuranceCoverageID": "1032",
              "TravelInsuranceCoverageTile": "پرداخت هزینه خریدهای اضطراری، در صورتیکه تأخیر در تحویل بار کنترل شده وی بیش از 12 ساعت به طول بیانجامد.",
              "TravelInsuranceCoverageVal": "200 یورو"
            },
            {
              "TravelInsuranceCoverageCategory": {
                "TravelInsuranceCoverageCatID": "2",
                "TravelInsuranceCoverageCatTile": null
              },
              "TravelInsuranceCoverageID": "1033",
              "TravelInsuranceCoverageTile": "مشاوره حقوقی و پرداخت هزینه های دعاوی  بیمه شده در صورتی که طبق قانون مدنی کشور مربوطه تحت پیگرد باشد.",
              "TravelInsuranceCoverageVal": "1,500 یورو"
            },
            {
              "TravelInsuranceCoverageCategory": {
                "TravelInsuranceCoverageCatID": "2",
                "TravelInsuranceCoverageCatTile": null
              },
              "TravelInsuranceCoverageID": "1034",
              "TravelInsuranceCoverageTile": "ارسال وجه الضمان",
              "TravelInsuranceCoverageVal": "850 یورو"
            },
            {
              "TravelInsuranceCoverageCategory": {
                "TravelInsuranceCoverageCatID": "2",
                "TravelInsuranceCoverageCatTile": null
              },
              "TravelInsuranceCoverageID": "1035",
              "TravelInsuranceCoverageTile": "حواله وجه نقد",
              "TravelInsuranceCoverageVal": "850 یورو"
            },
            {
              "TravelInsuranceCoverageCategory": {
                "TravelInsuranceCoverageCatID": "2",
                "TravelInsuranceCoverageCatTile": null
              },
              "TravelInsuranceCoverageID": "1036",
              "TravelInsuranceCoverageTile": "پرداخت هزینه رفت و برگشت یک نفر به درخواست بیمه شده از ایران به محل بستری در صورتیکه که بیمه شده بیش از 10 روز متوالی در بیمارستان بستری باشد.(شامل بلیط رفت و برگشت و مخارج اقامت)",
              "TravelInsuranceCoverageVal": "60یورو برای هر روز(15 روز متوالی)"
            },
            {
              "TravelInsuranceCoverageCategory": {
                "TravelInsuranceCoverageCatID": "2",
                "TravelInsuranceCoverageCatTile": null
              },
              "TravelInsuranceCoverageID": "1037",
              "TravelInsuranceCoverageTile": "بازگشت یکی از اعضای بلافصل خانواده به کشور محل اقامت در صورت بستری شدن بیمه شده بیش از 10 روز",
              "TravelInsuranceCoverageVal": "بدون سقف"
            },
            {
              "TravelInsuranceCoverageCategory": {
                "TravelInsuranceCoverageCatID": "2",
                "TravelInsuranceCoverageCatTile": null
              },
              "TravelInsuranceCoverageID": "1038",
              "TravelInsuranceCoverageTile": "کمک رسان پزشکی برای حوادث ورزشی(گلف،موج سواری،اسکی)",
              "TravelInsuranceCoverageVal": "10,000 یورو"
            },
            {
              "TravelInsuranceCoverageCategory": {
                "TravelInsuranceCoverageCatID": "2",
                "TravelInsuranceCoverageCatTile": null
              },
              "TravelInsuranceCoverageID": "1039",
              "TravelInsuranceCoverageTile": "پرداخت هزینه هایی که در صورت تاخیر هواپیما متوجه بیمه گذار خواهد بود ( اقامت در هتل صرف غذا ) با ارائه اصل صورتحساب و با تاییدیه شرکت هواپیمایی",
              "TravelInsuranceCoverageVal": "180 یورو"
            },
            {
              "TravelInsuranceCoverageCategory": {
                "TravelInsuranceCoverageCatID": "2",
                "TravelInsuranceCoverageCatTile": null
              },
              "TravelInsuranceCoverageID": "1040",
              "TravelInsuranceCoverageTile": "جبران هزینه‌های بازگشت زودهنگام بیمه شده به دلیل فوت یکی از بستگان بلافصل بیمه شده (به جز بستگانی که در مقصد سفر بیمه شده مقیم هستند)",
              "TravelInsuranceCoverageVal": "500 یورو"
            }
          ],
          "TravelInsuranceID": "-2",
          "TravelInsurancePricePP": {
            "Amount": 200000,
            "CurrencyCode": "IRR"
          },
          "TravelInsuranceTile": "بیمه مسافرتی سامان  - طرح تکمیلی"
        },
        {
          "InsID": "5",
          "TravelInsuranceCoverages": [
            {
              "TravelInsuranceCoverageCategory": {
                "TravelInsuranceCoverageCatID": "1",
                "TravelInsuranceCoverageCatTile": null
              },
              "TravelInsuranceCoverageID": "1000",
              "TravelInsuranceCoverageTile": "جبران هزینه‎‌های ناشی از کنسلی بلیط هواپیما یا کنسلی هتل محل اقامت به دلیل شرایط حاد اورژانسی بیمه شده که باعث بستری ایشان یا همراه وی شود.*همراه بیمه شده ( همراه سفر)یکی از بستگان درجه اول یا بلافصل بیمه شده شامل پدر، مادر، خواهر، همسر، فرزندیا فرزند خوانده قانونی است که با بیمه شده در یک پرواز و  به یک مقصد عازم مسافرت است",
              "TravelInsuranceCoverageVal": "500"
            },
            {
              "TravelInsuranceCoverageCategory": {
                "TravelInsuranceCoverageCatID": "1",
                "TravelInsuranceCoverageCatTile": null
              },
              "TravelInsuranceCoverageID": "1001",
              "TravelInsuranceCoverageTile": "جبران هزینه‌های ناشی از کنسلی بلیط هواپیما یا کنسلی هتل محل اقامت به دلیل بستری شدن یکی از اعضای بلافصل یا درجه اول بیمه شده دربیمارستان به دلیل شرایط اورژانسی (به جز بستگانی که در مقصد سفر بیمه شده مقیم هستند) - حداکثر 15 روز قبل از عزیمت به سفر.*همراه بیمه شده ( همراه سفر)یکی از بستگان درجه اول یا بلافصل بیمه شده شامل پدر، مادر، خواهر، همسر، فرزند یا فرزندخوانده قانونی است که با بیمه شده در یک پرواز و  به یک مقصد عازم مسافرت است.",
              "TravelInsuranceCoverageVal": "500"
            },
            {
              "TravelInsuranceCoverageCategory": {
                "TravelInsuranceCoverageCatID": "1",
                "TravelInsuranceCoverageCatTile": null
              },
              "TravelInsuranceCoverageID": "1002",
              "TravelInsuranceCoverageTile": "جبران هزینه‌های ناشی از کنسلی بلیط هواپیما یا هتل محل اقامت به دلیل عوارض ناشی از بارداری در 31 هفته اول بارداری بیمه شده یا یکی از اعضای بلافصل بیمه شده ( عوارض بارداری جندمین بارداری یا درمان عدم بارداری شامل این پوشش نیست).",
              "TravelInsuranceCoverageVal": "500"
            },
            {
              "TravelInsuranceCoverageCategory": {
                "TravelInsuranceCoverageCatID": "1",
                "TravelInsuranceCoverageCatTile": null
              },
              "TravelInsuranceCoverageID": "1003",
              "TravelInsuranceCoverageTile": "فوت بیمه شده",
              "TravelInsuranceCoverageVal": "500"
            },
            {
              "TravelInsuranceCoverageCategory": {
                "TravelInsuranceCoverageCatID": "1",
                "TravelInsuranceCoverageCatTile": null
              },
              "TravelInsuranceCoverageID": "1004",
              "TravelInsuranceCoverageTile": "جبران هزینه‌های ناشی از کنسلی بلیط هواپیما یا هتل محل اقامت به دلیل فوت یکی از بستگان بلافصل بیمه شده ( به جز بستگانی که در مقصد سفربیمه شده مقیم هستند)- حداکثر یک ماه قبل سفر به شرط این که متوفی بعد از خرید بیمه نامه فوت شده باشد.",
              "TravelInsuranceCoverageVal": "500"
            },
            {
              "TravelInsuranceCoverageCategory": {
                "TravelInsuranceCoverageCatID": "1",
                "TravelInsuranceCoverageCatTile": null
              },
              "TravelInsuranceCoverageID": "1005",
              "TravelInsuranceCoverageTile": "جبران هزینه‌های ناشی از کنسلی بلیط هواپیما یا کنسلی هتل محل اقامت به دلیل بستری شدن یکی از اعضای بلافصل یا درجه اول بیمه شده دربیمارستان به دلیل شرایط اورژانسی (به جز بستگانی که در مقصد سفر بیمه شده مقیم هستند) - حداکثر 30 روز قبل از عزیمت به سفر.همراه بیمه شده ( همراه سفر)",
              "TravelInsuranceCoverageVal": "500"
            },
            {
              "TravelInsuranceCoverageCategory": {
                "TravelInsuranceCoverageCatID": "1",
                "TravelInsuranceCoverageCatTile": null
              },
              "TravelInsuranceCoverageID": "1006",
              "TravelInsuranceCoverageTile": "جبران هزینه‌های ناشی از کنسلی بلیط هواپیما و یا هتل محل اقامت به دلیل اعلام رسمی وزرات امور خارجه جمهوری اسلامی ایران که در آن سفر افرادایرانی (مقیم ایران) به نقطه عزیمت  منع شده باشد، به شرط این که اعلامیه یاد شده پس از خرید بیمه نامه صورت پذیرفته باشد.",
              "TravelInsuranceCoverageVal": "500"
            },
            {
              "TravelInsuranceCoverageCategory": {
                "TravelInsuranceCoverageCatID": "1",
                "TravelInsuranceCoverageCatTile": null
              },
              "TravelInsuranceCoverageID": "1007",
              "TravelInsuranceCoverageTile": "جبران هزینه‌های ناشی از کنسلی بلیط هواپیما یا هتل محل اقامت به دلیل ازدست دادن پرواز به دلیل تصادف یا تاخیر وسیله حمل و نقل به فرودگاه محل عزیمت (این پوشش صرفا به شرکت تاکسی طرف قرارداد با شرکت بیمه سامان اعطا می شود).",
              "TravelInsuranceCoverageVal": "500"
            },
            {
              "TravelInsuranceCoverageCategory": {
                "TravelInsuranceCoverageCatID": "2",
                "TravelInsuranceCoverageCatTile": null
              },
              "TravelInsuranceCoverageID": "1008",
              "TravelInsuranceCoverageTile": "انتقال بیمه شده به نزدیکترین مرکز درمانی در اثر حادثه و یا بیماری هماهنگی های لازم جهت انتقال بیمه شده به مرکز درمانی مجهزتر، استفاده ازآمبولانس هوایی و یا بازگرداندن بیمه شده به ایران در صورت نیاز.",
              "TravelInsuranceCoverageVal": "بدون سقف"
            },
            {
              "TravelInsuranceCoverageCategory": {
                "TravelInsuranceCoverageCatID": "2",
                "TravelInsuranceCoverageCatTile": null
              },
              "TravelInsuranceCoverageID": "1009",
              "TravelInsuranceCoverageTile": "جبران هزینه‌های برگشت زود هنگام مسافر به دلیل شرایط حاد اورژانسی بیمه شده یا همراه وی در سفر.*همراه بیمه شده ( همراه سفر)یکی از بستگان درجه اول یا بلافصل بیمه شده شامل پدر، مادر، خواهر، همسر، فرزند یا فرزند خوانده قانونی است که با بیمه شده در یک پرواز و  به یک مقصد عازم مسافرت است.",
              "TravelInsuranceCoverageVal": "500"
            },
            {
              "TravelInsuranceCoverageCategory": {
                "TravelInsuranceCoverageCatID": "2",
                "TravelInsuranceCoverageCatTile": null
              },
              "TravelInsuranceCoverageID": "1010",
              "TravelInsuranceCoverageTile": "مسئولیت شخصی",
              "TravelInsuranceCoverageVal": "2,000"
            },
            {
              "TravelInsuranceCoverageCategory": {
                "TravelInsuranceCoverageCatID": "2",
                "TravelInsuranceCoverageCatTile": null
              },
              "TravelInsuranceCoverageID": "1011",
              "TravelInsuranceCoverageTile": "پرداخت هزینه بستری شدن در بیمارستان و معالجات پزشکی (با استثناء هزینه های زیبایی ، بیماری های که از قبل سابقه داشته باشد ) فرانشیز 25 یورو",
              "TravelInsuranceCoverageVal": "20,000"
            },
            {
              "TravelInsuranceCoverageCategory": {
                "TravelInsuranceCoverageCatID": "2",
                "TravelInsuranceCoverageCatTile": null
              },
              "TravelInsuranceCoverageID": "1012",
              "TravelInsuranceCoverageTile": "پرداخت هزینه فوریت های دندانپزشکی ، فرانشیز 25 یورو",
              "TravelInsuranceCoverageVal": "250"
            },
            {
              "TravelInsuranceCoverageCategory": {
                "TravelInsuranceCoverageCatID": "2",
                "TravelInsuranceCoverageCatTile": null
              },
              "TravelInsuranceCoverageID": "1013",
              "TravelInsuranceCoverageTile": "تجویز دارو",
              "TravelInsuranceCoverageVal": "400"
            },
            {
              "TravelInsuranceCoverageCategory": {
                "TravelInsuranceCoverageCatID": "2",
                "TravelInsuranceCoverageCatTile": null
              },
              "TravelInsuranceCoverageID": "1014",
              "TravelInsuranceCoverageTile": "هزینه های هتل (مربوط به دوران نقاهت و بستری)",
              "TravelInsuranceCoverageVal": "400"
            },
            {
              "TravelInsuranceCoverageCategory": {
                "TravelInsuranceCoverageCatID": "2",
                "TravelInsuranceCoverageCatTile": null
              },
              "TravelInsuranceCoverageID": "1015",
              "TravelInsuranceCoverageTile": "هزینه های هتل همراهان وبستگان (در زمان بستری بیمه شده)",
              "TravelInsuranceCoverageVal": "300"
            },
            {
              "TravelInsuranceCoverageCategory": {
                "TravelInsuranceCoverageCatID": "2",
                "TravelInsuranceCoverageCatTile": null
              },
              "TravelInsuranceCoverageID": "1016",
              "TravelInsuranceCoverageTile": "پرداخت هزینه های بازگشت کودکان زیر 15 سال بیمه شده به همراه یک سرپرست به ایران در صورت فوت یا بستری شدن بیمه شده",
              "TravelInsuranceCoverageVal": "بدون سقف"
            },
            {
              "TravelInsuranceCoverageCategory": {
                "TravelInsuranceCoverageCatID": "2",
                "TravelInsuranceCoverageCatTile": null
              },
              "TravelInsuranceCoverageID": "1017",
              "TravelInsuranceCoverageTile": "پرداخت هزینه های جابه جایی اورژانسی به دلیل مشکلات پزشکی تا اولین مرکز درمانی",
              "TravelInsuranceCoverageVal": "بدون سقف"
            },
            {
              "TravelInsuranceCoverageCategory": {
                "TravelInsuranceCoverageCatID": "2",
                "TravelInsuranceCoverageCatTile": null
              },
              "TravelInsuranceCoverageID": "1018",
              "TravelInsuranceCoverageTile": "ارسال دارو های ضروری با تائید پرشکی به کشوری که بیمه شده درآن بستری می باشد.",
              "TravelInsuranceCoverageVal": "بدون سقف"
            },
            {
              "TravelInsuranceCoverageCategory": {
                "TravelInsuranceCoverageCatID": "2",
                "TravelInsuranceCoverageCatTile": null
              },
              "TravelInsuranceCoverageID": "1019",
              "TravelInsuranceCoverageTile": "ارسال پیام های فوری بیمه شده به فردی که توسط وی معرفی شده و همچنین ارائه نشانی مراکز درمانی، داروخانه ها، پزشکان به بیمه شده در خارج از کشور",
              "TravelInsuranceCoverageVal": "بدون سقف"
            },
            {
              "TravelInsuranceCoverageCategory": {
                "TravelInsuranceCoverageCatID": "2",
                "TravelInsuranceCoverageCatTile": null
              },
              "TravelInsuranceCoverageID": "1020",
              "TravelInsuranceCoverageTile": "کمک رسان در دسترس 24 ساعته،7 روز هفته به زبان فارسی",
              "TravelInsuranceCoverageVal": "تحت پوشش"
            },
            {
              "TravelInsuranceCoverageCategory": {
                "TravelInsuranceCoverageCatID": "2",
                "TravelInsuranceCoverageCatTile": null
              },
              "TravelInsuranceCoverageID": "1021",
              "TravelInsuranceCoverageTile": "هزینه جستجو ونجات بیمه شده",
              "TravelInsuranceCoverageVal": "3,000"
            },
            {
              "TravelInsuranceCoverageCategory": {
                "TravelInsuranceCoverageCatID": "2",
                "TravelInsuranceCoverageCatTile": null
              },
              "TravelInsuranceCoverageID": "1022",
              "TravelInsuranceCoverageTile": "پرداخت هزینه بازگشت غیر منتظره بیمه شده به دلیل مسائل حاد پزشکی ",
              "TravelInsuranceCoverageVal": "10,000"
            },
            {
              "TravelInsuranceCoverageCategory": {
                "TravelInsuranceCoverageCatID": "2",
                "TravelInsuranceCoverageCatTile": null
              },
              "TravelInsuranceCoverageID": "1023",
              "TravelInsuranceCoverageTile": "بازگرداندن جسد بیمه شده متوفی به ایران در صورت فوت وی درخارج از کشور",
              "TravelInsuranceCoverageVal": "10,000"
            },
            {
              "TravelInsuranceCoverageCategory": {
                "TravelInsuranceCoverageCatID": "2",
                "TravelInsuranceCoverageCatTile": null
              },
              "TravelInsuranceCoverageID": "1024",
              "TravelInsuranceCoverageTile": "پرداخت هزینه بازگشت غیر منتظره بیمه شده به دلیل مسائل حاد پزشکی و یا فوت بستگان در صورتیکه نتواند از بلیط اصلی برای بازگشت استفاده نماید.",
              "TravelInsuranceCoverageVal": "بدون سقف"
            },
            {
              "TravelInsuranceCoverageCategory": {
                "TravelInsuranceCoverageCatID": "2",
                "TravelInsuranceCoverageCatTile": null
              },
              "TravelInsuranceCoverageID": "1025",
              "TravelInsuranceCoverageTile": "کنسل شدن سفر به دلیل فوت بیمه شده (هزینه های تور بلیط هواپیما)",
              "TravelInsuranceCoverageVal": "500"
            },
            {
              "TravelInsuranceCoverageCategory": {
                "TravelInsuranceCoverageCatID": "2",
                "TravelInsuranceCoverageCatTile": null
              },
              "TravelInsuranceCoverageID": "1026",
              "TravelInsuranceCoverageTile": "هزینه های کنسل شدن سفر (شامل تور وبلیط)به دلیل فوت بستگان بلا فصل حد اکثر 14 روز قبل سفر",
              "TravelInsuranceCoverageVal": "300"
            },
            {
              "TravelInsuranceCoverageCategory": {
                "TravelInsuranceCoverageCatID": "2",
                "TravelInsuranceCoverageCatTile": null
              },
              "TravelInsuranceCoverageID": "1027",
              "TravelInsuranceCoverageTile": "هزینه های کنسل شدن سفر (شامل تور وبلیط)به دلیل بستری شدن بیمه شده به صورتی که بیمه شده تا زمان سفر بستری باشد",
              "TravelInsuranceCoverageVal": "400"
            },
            {
              "TravelInsuranceCoverageCategory": {
                "TravelInsuranceCoverageCatID": "2",
                "TravelInsuranceCoverageCatTile": null
              },
              "TravelInsuranceCoverageID": "1028",
              "TravelInsuranceCoverageTile": "یافتن بار و ارسال بار و ملزومات شخصی ( طبق شرایط عمومی بیمه نامه مسافرتی شرکت کمک رسان ایران )",
              "TravelInsuranceCoverageVal": "بدون سقف"
            },
            {
              "TravelInsuranceCoverageCategory": {
                "TravelInsuranceCoverageCatID": "2",
                "TravelInsuranceCoverageCatTile": null
              },
              "TravelInsuranceCoverageID": "1029",
              "TravelInsuranceCoverageTile": "هزینه جبران مفقود شدن یا گم شدن جامه دان و اسباب همراه ( به استثنا دزدی و سرقت )",
              "TravelInsuranceCoverageVal": "400"
            },
            {
              "TravelInsuranceCoverageCategory": {
                "TravelInsuranceCoverageCatID": "2",
                "TravelInsuranceCoverageCatTile": null
              },
              "TravelInsuranceCoverageID": "1030",
              "TravelInsuranceCoverageTile": "راهنمایی و کمک رسانی به بیمه شده در صورت سرقت و یا مفقود شدن مدارک مسافرتی وی.",
              "TravelInsuranceCoverageVal": "800"
            },
            {
              "TravelInsuranceCoverageCategory": {
                "TravelInsuranceCoverageCatID": "2",
                "TravelInsuranceCoverageCatTile": null
              },
              "TravelInsuranceCoverageID": "1031",
              "TravelInsuranceCoverageTile": "پرداخت هزینه خریدهای اضطراری، در صورتیکه تأخیر در تحویل بار کنترل شده وی بیش از 48 ساعت به طول بیانجامد.",
              "TravelInsuranceCoverageVal": "800"
            },
            {
              "TravelInsuranceCoverageCategory": {
                "TravelInsuranceCoverageCatID": "2",
                "TravelInsuranceCoverageCatTile": null
              },
              "TravelInsuranceCoverageID": "1032",
              "TravelInsuranceCoverageTile": "پرداخت هزینه خریدهای اضطراری، در صورتیکه تأخیر در تحویل بار کنترل شده وی بیش از 12 ساعت به طول بیانجامد.",
              "TravelInsuranceCoverageVal": "200"
            },
            {
              "TravelInsuranceCoverageCategory": {
                "TravelInsuranceCoverageCatID": "2",
                "TravelInsuranceCoverageCatTile": null
              },
              "TravelInsuranceCoverageID": "1033",
              "TravelInsuranceCoverageTile": "مشاوره حقوقی و پرداخت هزینه های دعاوی  بیمه شده در صورتی که طبق قانون مدنی کشور مربوطه تحت پیگرد باشد.",
              "TravelInsuranceCoverageVal": "1,500"
            },
            {
              "TravelInsuranceCoverageCategory": {
                "TravelInsuranceCoverageCatID": "2",
                "TravelInsuranceCoverageCatTile": null
              },
              "TravelInsuranceCoverageID": "1034",
              "TravelInsuranceCoverageTile": "ارسال وجه الضمان",
              "TravelInsuranceCoverageVal": "850"
            },
            {
              "TravelInsuranceCoverageCategory": {
                "TravelInsuranceCoverageCatID": "2",
                "TravelInsuranceCoverageCatTile": null
              },
              "TravelInsuranceCoverageID": "1035",
              "TravelInsuranceCoverageTile": "حواله وجه نقد",
              "TravelInsuranceCoverageVal": "850"
            },
            {
              "TravelInsuranceCoverageCategory": {
                "TravelInsuranceCoverageCatID": "2",
                "TravelInsuranceCoverageCatTile": null
              },
              "TravelInsuranceCoverageID": "1036",
              "TravelInsuranceCoverageTile": "پرداخت هزینه رفت و برگشت یک نفر به درخواست بیمه شده از ایران به محل بستری در صورتیکه که بیمه شده بیش از 10 روز متوالی در بیمارستان بستری باشد.(شامل بلیط رفت و برگشت و مخارج اقامت)",
              "TravelInsuranceCoverageVal": "60یورو برای هر روز(15 روز متوالی)"
            },
            {
              "TravelInsuranceCoverageCategory": {
                "TravelInsuranceCoverageCatID": "2",
                "TravelInsuranceCoverageCatTile": null
              },
              "TravelInsuranceCoverageID": "1037",
              "TravelInsuranceCoverageTile": "بازگشت یکی از اعضای بلافصل خانواده به کشور محل اقامت در صورت بستری شدن بیمه شده بیش از 10 روز",
              "TravelInsuranceCoverageVal": "بدون سقف"
            },
            {
              "TravelInsuranceCoverageCategory": {
                "TravelInsuranceCoverageCatID": "2",
                "TravelInsuranceCoverageCatTile": null
              },
              "TravelInsuranceCoverageID": "1038",
              "TravelInsuranceCoverageTile": "کمک رسان پزشکی برای حوادث ورزشی(گلف،موج سواری،اسکی)",
              "TravelInsuranceCoverageVal": "10,000"
            },
            {
              "TravelInsuranceCoverageCategory": {
                "TravelInsuranceCoverageCatID": "2",
                "TravelInsuranceCoverageCatTile": null
              },
              "TravelInsuranceCoverageID": "1039",
              "TravelInsuranceCoverageTile": "پرداخت هزینه هایی که در صورت تاخیر هواپیما متوجه بیمه گذار خواهد بود ( اقامت در هتل صرف غذا ) با ارائه اصل صورتحساب و با تاییدیه شرکت هواپیمایی",
              "TravelInsuranceCoverageVal": "180"
            },
            {
              "TravelInsuranceCoverageCategory": {
                "TravelInsuranceCoverageCatID": "2",
                "TravelInsuranceCoverageCatTile": null
              },
              "TravelInsuranceCoverageID": "1040",
              "TravelInsuranceCoverageTile": "جبران هزینه‌های بازگشت زودهنگام بیمه شده به دلیل فوت یکی از بستگان بلافصل بیمه شده (به جز بستگانی که در مقصد سفر بیمه شده مقیم هستند)",
              "TravelInsuranceCoverageVal": "500"
            }
          ],
          "TravelInsuranceID": "-3",
          "TravelInsurancePricePP": {
            "Amount": 300000,
            "CurrencyCode": "IRR"
          },
          "TravelInsuranceTile": "بیمه مسافرتی سامان  - طرح جامع"
        }
      ]
    }
  }
}